[1,0,0,[["cc.JsonAsset",["_name","json"],1]],[[0,0,1,3]],[[0,"LevelSelectConfig",[{"levelID":1,"levelName":"皇宫聚餐","resourceKey":"level1"},{"levelID":2,"levelName":"热闹集市","resourceKey":"level19"},{"levelID":3,"levelName":"王子驾到","resourceKey":"level24"},{"levelID":4,"levelName":"雪中行军","resourceKey":"level33"},{"levelID":5,"levelName":"铁王座下","resourceKey":"level47"},{"levelID":6,"levelName":"修船大计","resourceKey":"level49"},{"levelID":7,"levelName":"午餐时光","resourceKey":"level11"},{"levelID":8,"levelName":"火焰表演","resourceKey":"level14"},{"levelID":9,"levelName":"这菜有毒","resourceKey":"level56"},{"levelID":10,"levelName":"画中有你","resourceKey":"level53"},{"levelID":11,"levelName":"码头接待","resourceKey":"level7"},{"levelID":12,"levelName":"冬日闹市","resourceKey":"level21"}]]],0,0,[],[],[]]
